{
  "product_cd": "1000039814",
  "scraped_at": "2026-05-07T13:00:51.747Z",
  "total": 50,
  "reviews": [
    {
      "id": "608838",
      "rating": 5,
      "name": "네****",
      "content": "너무 귀여워요 싸이즈가 너무 좋아요 젠자렌지에 돌리기도 좋고 화식 해동할때 냉장보관 하기도 좋아요",
      "date": "2026-05-05T19:22:12+09:00",
      "images": [
        "https://assets6.cre.ma/p/biteme-co-kr/reviews/00/00/60/88/38/image1/41ca91f3c8a24dcd.webp"
      ],
      "content_ja": "すごく可愛いです！サイズ感もぴったりで、電子レンジで温めるのも便利だし、ご飯を解凍する時に冷蔵保管するのにも最適です",
      "content_en": "It's so cute and the size is perfect! 😊 It's great for microwaving and also convenient for storing in the fridge when thawing wet food.",
      "videos": []
    },
    {
      "id": "608369",
      "rating": 5,
      "name": "네****",
      "content": "약간 작은 느낌이라 중대형견한테는 작을수도있겠다싶었어요! 대시뚜껑있고 전자렌지 열탕소독도가능해서최고",
      "date": "2026-04-30T17:16:01+09:00",
      "images": [
        "https://assets6.cre.ma/p/biteme-co-kr/reviews/00/00/60/83/69/image1/979b6e7215b2df00.webp"
      ],
      "content_ja": "少し小さめな感じがするので、中大型犬には小さいかもって思いました！でも蓋付きで電子レンジと熱湯消毒も対応できるから最高です",
      "content_en": "It felt a bit small, so I thought it might be too small for large breed dogs! But it comes with a lid and you can microwave sterilize it, so it's the best.",
      "videos": []
    },
    {
      "id": "607619",
      "rating": 5,
      "name": "네****",
      "content": "너무 맘에 들어요\n강아지 외출할때 간식도 담아서 들고 \n나가고 소리도 안나고 뚜껑까지 있어서\n아주 좋아요",
      "date": "2026-04-28T09:09:41+09:00",
      "images": [
        "https://assets6.cre.ma/p/biteme-co-kr/reviews/00/00/60/76/19/image1/3955ac07b844ef5a.webp"
      ],
      "content_ja": "すごく気に入りました💕\n犬のお出かけの時にオヤツも入れて持ち運べるし、音もしないし蓋までついてるから本当に便利です",
      "content_en": "I love it so much 💕 I can pack treats when taking my pup out, it doesn't make noise, and it has a lid so it's really great!",
      "videos": []
    },
    {
      "id": "605645",
      "rating": 5,
      "name": "정****",
      "content": "전에 이거보다 큰 실리콘 팟 구매하고 여행갈때마다 잘 써서 이번에는 작은걸로 구매해봤어요 중형견이라 밥그릇하기에 조금 작은감이 있긴한데 습식같은거 딱 한끼 하기에는 괜찮은거같아요 귀엽고 뚜껑도 안벗겨지고 전자렌지 사용도 가능하고 마음에 들어요",
      "date": "2026-04-19T02:10:19+09:00",
      "images": [
        "https://assets6.cre.ma/p/biteme-co-kr/reviews/00/00/60/56/45/image1/96f85993057cf557.webp"
      ],
      "content_ja": "前に使ってた大きいシリコンパッドが旅行の時に重宝してたから、今回は小さめを買ってみました。中型犬なので食器としては少し小さい感じはありますが、ウェットフードとか1食分には丁度いいと思います。可愛くて蓋も取れないし、電子レンジも使えるし気に入ってます😊",
      "content_en": "I bought a bigger silicone bowl before this and used it well every time we traveled, so this time I got the smaller size. Since I have a medium-sized dog, it's a bit small for a regular food bowl, but it seems perfect for a single serving of wet food. It's cute, the lid doesn't come off, microwave safe, and I'm really happy with it.",
      "videos": []
    },
    {
      "id": "605121",
      "rating": 5,
      "name": "김****",
      "content": "엄마가 택배 먼저 집에서 받으셨는데 요기다가 찬밥을ㅋㅋㅋㅋ\n강아지꺼라고 하니까 가볍고 좋다며 아쉬워하시고 탐내시더라고요😂 \n멈머 평소 밥차려주기도 좋고 봄맞이 소풍가고 싶어서 시켜봤어요 다른색도 엄청 귀여울듯!",
      "date": "2026-04-02T10:17:15+09:00",
      "images": [
        "https://assets6.cre.ma/p/biteme-co-kr/reviews/00/00/60/51/21/image1/6bb994cd151fae4b.webp"
      ],
      "content_ja": "ママが先に宅配で受け取ったんですけど、ここに冷ご飯をwww\n犬用だって言ったら軽いし便利だって残念がってて欲しがってましたww😂\nママも普段ご飯をよそう時に便利だし、春だからお弁当を持ってお出かけしたくなって買ってみました。他の色もめっちゃ可愛いと思います！",
      "content_en": "My mom got the package first at home and she put cold rice in it ㅋㅋㅋㅋ When I told her it was for my dog, she was bummed and kept eyeing it 😂 It's convenient for my mom's meal prep too, and I bought it because I wanted to go on a spring picnic with my pup. The other colors are super cute too!",
      "videos": []
    },
    {
      "id": "604733",
      "rating": 5,
      "name": "주****",
      "content": "바잇미 실리콘 팟 큰걸 구매해서 사용하고 있었는데 좀 더 작으면 좋겠다 싶어서 구매했어요! 놀러갈때 작은건 건사료, 큰건 동결건조 이렇게 사용하려구요~",
      "date": "2026-03-25T01:18:19+09:00",
      "images": [
        "https://assets6.cre.ma/p/biteme-co-kr/reviews/00/00/60/47/33/image1/e62ab6176d1841cc.webp"
      ],
      "content_ja": "バイトミのシリコンパッド大きいサイズを使ってるんですけど、もう少し小さいサイズがあればいいなって思って購入しました！お出かけの時は小さいのはドライフード、大きいのは凍結乾燥食をって使い分けるつもりです～",
      "content_en": "I was using the larger BITE ME silicone bowl and wanted something smaller, so I got this! When we go out, I'm planning to use the small one for dry food and the large one for freeze-dried treats~ 🐕",
      "videos": []
    },
    {
      "id": "603901",
      "rating": 4,
      "name": "네****",
      "content": "생각보다작아서 계산착오예요..ㅠ그래도써야죠",
      "date": "2026-03-12T09:47:16+09:00",
      "images": [
        "https://assets6.cre.ma/p/biteme-co-kr/reviews/00/00/60/39/01/image1/1549058f313d0a5a.webp"
      ],
      "content_ja": "思ったより小さくて、計算間違いでした...😭でも使いますけど",
      "content_en": "It's smaller than I expected... my bad on the math 😅 But I'll still use it.",
      "videos": []
    },
    {
      "id": "603961",
      "rating": 5,
      "name": "네****",
      "content": "그릇도 너무 이쁘지만 편의성.실용성도 모두 만족스럽습니다:)",
      "date": "2026-03-11T18:22:21+09:00",
      "images": [
        "https://assets6.cre.ma/p/biteme-co-kr/reviews/00/00/60/39/61/image1/11557334bab896d4.webp"
      ],
      "content_ja": "器も本当に可愛いですが、利便性と実用性も両方満足です😊",
      "content_en": "The bowl is so pretty, but the convenience and practicality are all really satisfying too :)",
      "videos": []
    },
    {
      "id": "603962",
      "rating": 5,
      "name": "네****",
      "content": "그릇도 너무 이쁘지만 편의성.실용성도 모두 만족스럽습니다:)",
      "date": "2026-03-11T18:21:54+09:00",
      "images": [
        "https://assets6.cre.ma/p/biteme-co-kr/reviews/00/00/60/39/62/image1/f544bb9c4c6284c0.webp"
      ],
      "content_ja": "器も本当に可愛いですが、利便性と実用性も両方満足です😊",
      "content_en": "The bowl is so pretty, but the convenience and practicality are all really satisfying too :)",
      "videos": []
    },
    {
      "id": "603168",
      "rating": 5,
      "name": "네****",
      "content": "추천받아서 샀는데 너무 좋아요!",
      "date": "2026-03-06T19:13:50+09:00",
      "images": [
        "https://assets6.cre.ma/p/biteme-co-kr/reviews/00/00/60/31/68/image1/aecd0518dbf486d1.webp"
      ],
      "content_ja": "おすすめされて買ったんですけど、本当に良いです！",
      "content_en": "Someone recommended it and I bought it - I absolutely love it! 🐾",
      "videos": []
    },
    {
      "id": "603003",
      "rating": 5,
      "name": "네****",
      "content": "떨어트려도 안깨재고 소리도 안나고 좋아요",
      "date": "2026-03-05T21:49:51+09:00",
      "images": [
        "https://assets6.cre.ma/p/biteme-co-kr/reviews/00/00/60/30/03/image1/d1e9cacd938f73bd.webp"
      ],
      "content_ja": "落としても割れないし、音もしなくて良いです",
      "content_en": "It's great - doesn't break even when dropped and makes no noise 😊",
      "videos": []
    },
    {
      "id": "603004",
      "rating": 5,
      "name": "네****",
      "content": "생각보다 작네여 기여워용",
      "date": "2026-03-05T21:49:05+09:00",
      "images": [
        "https://assets6.cre.ma/p/biteme-co-kr/reviews/00/00/60/30/04/image1/6ff7802e0b47c547.webp"
      ],
      "content_ja": "思ったより小さいですね、可愛いです",
      "content_en": "It's smaller than I thought, but it's adorable 🥰",
      "videos": []
    },
    {
      "id": "602712",
      "rating": 5,
      "name": "네****",
      "content": "예전에 이거보다 큰 사이즈 보라색 잘 사용하다가 \n봄맞이 새로 샀어요 ㅋㅋ 강아지가 사료를 잘 안 먹어서 이 크기가 더 좋은 것 같아요!",
      "date": "2026-03-02T17:18:17+09:00",
      "images": [
        "https://assets6.cre.ma/p/biteme-co-kr/reviews/00/00/60/27/12/image1/c313611ab00fac9e.webp"
      ],
      "content_ja": "以前はこれより大きい紫色のサイズを使ってて、春に向けて新しく買いました ㅋㅋ わんちゃんがドッグフードをあまり食べないので、このサイズの方が良さそうです！",
      "content_en": "I used to buy the bigger purple version of this, but got a new one for spring ㅋㅋ My dog wasn't eating well, so this smaller size seems to work better!",
      "videos": []
    },
    {
      "id": "602792",
      "rating": 5,
      "name": "네****",
      "content": "튼튼 짱짱 이쁩니다..휴대용으로 구매 잘산거 같아요",
      "date": "2026-03-01T23:36:05+09:00",
      "images": [
        "https://assets6.cre.ma/p/biteme-co-kr/reviews/00/00/60/27/92/image1/a1cd915309152141.webp"
      ],
      "content_ja": "丈夫でしっかり、可愛いです..携帯用として購入できてよかったです",
      "content_en": "Sturdy and solid, looks great too.. I think it was a good buy for portability 😊",
      "videos": []
    },
    {
      "id": "601701",
      "rating": 5,
      "name": "네****",
      "content": "총알배송 상품도 왕왕 맘에들어요 아이도 사용 잘합니다 색이 예뻐요",
      "date": "2026-02-24T18:48:25+09:00",
      "images": [
        "https://assets6.cre.ma/p/biteme-co-kr/reviews/00/00/60/17/01/image1/a436326255f17ac2.webp"
      ],
      "content_ja": "超高速配送の商品も本当に気に入ってます。子どもも使いやすいです。色が可愛いですね",
      "content_en": "The quick shipping items are always great, and my pet uses it well too! The color is really pretty 💕",
      "videos": []
    },
    {
      "id": "601702",
      "rating": 5,
      "name": "네****",
      "content": "총알배송 상품도 왕왕 맘에들어요 아이도 사용 잘합니다 색이 예뻐요",
      "date": "2026-02-24T18:48:05+09:00",
      "images": [
        "https://assets6.cre.ma/p/biteme-co-kr/reviews/00/00/60/17/02/image1/da6f97345a4c2b8c.webp"
      ],
      "content_ja": "超高速配送の商品も本当に気に入ってます。子どもも使いやすいです。色が可愛いですね",
      "content_en": "The quick shipping items are always great, and my pet uses it well too! The color is really pretty 💕",
      "videos": []
    },
    {
      "id": "601790",
      "rating": 5,
      "name": "네****",
      "content": "유해성분 없는 실리콘 그릇이라서 안심됩니다.",
      "date": "2026-02-24T00:20:11+09:00",
      "images": [
        "https://assets6.cre.ma/p/biteme-co-kr/reviews/00/00/60/17/90/image1/7d47e1c911b7ccae.webp"
      ],
      "content_ja": "有害成分のないシリコン製のボウルなので安心です",
      "content_en": "I feel reassured knowing it's a silicone bowl with no harmful chemicals.",
      "videos": []
    },
    {
      "id": "601391",
      "rating": 5,
      "name": "우****",
      "content": "귀엽고 컴팩트한 사이즈네요 들고 다니기 편할 거 같아요\n여행 갈 때 좋을듯!!",
      "date": "2026-02-22T21:07:07+09:00",
      "images": [
        "https://assets6.cre.ma/p/biteme-co-kr/reviews/00/00/60/13/91/image1/51668b76c169c8b0.webp"
      ],
      "content_ja": "可愛くてコンパクトなサイズですね。持ち歩きやすそうです。旅行のときにいいですね!!",
      "content_en": "It's cute and a compact size! It'll be really convenient to carry around 🎒 Perfect for trips!! ✈️",
      "videos": []
    },
    {
      "id": "600128",
      "rating": 5,
      "name": "네****",
      "content": "잘사용하고ㅈ있습니디ㅡ 미니팟은ㅈ버터색보다 쨍한 노란색이 더이쁩니다",
      "date": "2026-02-11T21:06:06+09:00",
      "images": [
        "https://assets6.cre.ma/p/biteme-co-kr/reviews/00/00/60/01/28/image1/86017a57bc842366.webp"
      ],
      "content_ja": "よく使っています。ミニポットはバター色よりも鮮やかな黄色の方がもっと可愛いです",
      "content_en": "Using it well! 😊 The mini pot looks better in a bright yellow color than butter color 💛",
      "videos": []
    },
    {
      "id": "599822",
      "rating": 5,
      "name": "네****",
      "content": "좋아요 좋아요 좋아요",
      "date": "2026-02-09T15:38:45+09:00",
      "images": [
        "https://assets6.cre.ma/p/biteme-co-kr/reviews/00/00/59/98/22/image1/16e364d967d20197.webp"
      ],
      "content_ja": "いいです いいです いいです",
      "content_en": "Love it love it love it 💕",
      "videos": []
    },
    {
      "id": "599260",
      "rating": 5,
      "name": "네****",
      "content": "이뻐요색상도\n사이즈도소형견딱입니다",
      "date": "2026-02-05T13:22:46+09:00",
      "images": [
        "https://assets6.cre.ma/p/biteme-co-kr/reviews/00/00/59/92/60/image1/178abe020a23df14.webp"
      ],
      "content_ja": "かわいいです！色合いもサイズも小型犬にぴったりです。",
      "content_en": "It's pretty and the color is nice too. The size is perfect for small dogs.",
      "videos": []
    },
    {
      "id": "598186",
      "rating": 5,
      "name": "네****",
      "content": "강아지 유치원 도시락 보낼때 좋아요.\n기존에 큰 사이즈 썼었는데, 작은사이즈가 등원가방에 쏙들어가고 좋네요 ㅎㅎ",
      "date": "2026-01-23T16:47:08+09:00",
      "images": [
        "https://assets6.cre.ma/p/biteme-co-kr/reviews/00/00/59/81/86/image1/4e1afa03dc1baf66.webp"
      ],
      "content_ja": "ワンちゃんの幼稚園のお弁当を持たせるときに良いですよ。これまで大きいサイズを使っていたんですが、小さいサイズが登園カバンにぴったり収まって便利です😄",
      "content_en": "Great for sending to puppy daycare! I used to use the larger size, but the small one fits perfectly in the school bag 😄",
      "videos": []
    },
    {
      "id": "595520",
      "rating": 4,
      "name": "김****",
      "content": "귀엽다 크기가 외출용으로 너무 좋다 뚜껑도 꽤나 견고하게 닫힌다. 조금 저렴하면 좋겠지만 마음에 든다",
      "date": "2025-12-25T21:13:42+09:00",
      "images": [
        "https://assets6.cre.ma/p/biteme-co-kr/reviews/00/00/59/55/20/image1/353c83e9941ee10c.webp"
      ],
      "content_ja": "かわいい💕サイズもお出かけ用にぴったり👍蓋もしっかりと閉まります。もう少し安いと嬉しいですが、とても気に入っています😊",
      "content_en": "Cute and the size is perfect for going out. The lid closes pretty securely. I wish it were a bit cheaper, but I'm happy with it.",
      "videos": []
    },
    {
      "id": "594126",
      "rating": 5,
      "name": "김****",
      "content": "색상이 아주 마음에 들어요! 생각했던 크기라서 흡족😊\n5kg 이내의 크기를 가진 아이들한테 작은 그릇은 아니에요\n동생한테 의견 안 물어보고 마음대로 주문했는데 재질,색상 다 만족스럽고 잘 샀다고 칭찬들음ㅋㅋㅋ",
      "date": "2025-11-26T08:47:40+09:00",
      "images": [
        "https://assets6.cre.ma/p/biteme-co-kr/reviews/00/00/59/41/26/image1/be47b8e32eb59d4b.webp"
      ],
      "content_ja": "色合いがとても気に入りました！想像していたサイズで満足です😊\n5kg以下のサイズのワンちゃんにとって、決して小さい食器ではありませんよ\n弟に相談せずに勝手に注文しちゃったんですが、素材も色合いも満足で、良い買い物ができたと褒められました😄",
      "content_en": "I love the color! It's the size I expected, so I'm satisfied 😊 For pets under 5kg, it's definitely not a small bowl. I ordered it without asking my sibling's opinion, but the material and color are all satisfactory—they even complimented me on the purchase ㅋㅋㅋ",
      "videos": []
    },
    {
      "id": "593216",
      "rating": 5,
      "name": "구****",
      "content": "기존에 휴대용 접이식그릇을 잘 사용하고 있어서 바잇미식기 할인하길래 언능 구매했어요~ 기존 세라믹식기는 소리에 예민하게 반응했는데  확실히 실리콘이라 소리가 안나니 거부감없이 즐겁게 식사하네용~ 아참 뚜껑있는거 너무 좋아요 입짧은 울 댕댕이를 위해서 맞춤입니다",
      "date": "2025-11-10T23:05:15+09:00",
      "images": [
        "https://assets6.cre.ma/p/biteme-co-kr/reviews/00/00/59/32/16/image1/8a4763b0562c8862.webp"
      ],
      "content_ja": "これまで携帯用の折りたたみ食器を使ってたので、バイトミ食器がセール中だったから早速購入しました～✨従来のセラミック食器は音に敏感に反応していたんですが、シリコンだからこそ音がしないので、ストレスなく楽しく食事しています～😋あ、蓋があるのが本当に良いですね！口の小さいうちの子ぴったりです💕",
      "content_en": "I was already using a portable collapsible bowl, so when BITE ME dinnerware went on sale, I bought it right away! My ceramic dishes used to make my pup react sensitively to the noise, but since this is silicone, there's no sound at all—now mealtime is stress-free and happy! And I really love that it has a lid. It's perfect for my short-muzzled pup!",
      "videos": []
    },
    {
      "id": "592689",
      "rating": 5,
      "name": "이****",
      "content": "최고에요 화식 데우는데 편해요",
      "date": "2025-11-01T09:24:34+09:00",
      "images": [
        "https://assets6.cre.ma/p/biteme-co-kr/reviews/00/00/59/26/89/image1/c37b0415f04d3cd6.webp"
      ],
      "content_ja": "最高です！温かいご飯を温めるのに便利ですよ😊",
      "content_en": "The best! It's convenient for heating up wet food.",
      "videos": []
    },
    {
      "id": "591854",
      "rating": 5,
      "name": "최****",
      "content": "디자인 실용성 무게 모두 다 만족이요~\n가격도 착해요♡♡",
      "date": "2025-10-17T11:52:47+09:00",
      "images": [
        "https://assets6.cre.ma/p/biteme-co-kr/reviews/00/00/59/18/54/image1/0183b7a2f334d6b5.webp"
      ],
      "content_ja": "デザイン、実用性、重さ、全て満足です～🌟\nお値段もお手頃で嬉しい♡♡",
      "content_en": "I'm satisfied with everything—the design, functionality, and weight! The price is great too ♡♡",
      "videos": []
    },
    {
      "id": "591709",
      "rating": 5,
      "name": "공****",
      "content": "큰거랑 작은거 둘 다 잘 쓰고있어서 추가로 구입했어요~~\n실제 색상이 조금 더 진해요 머스타드 같은 느낌?\n유치원 도시락으로 챙겨 다니기 딱 좋아요 💛",
      "date": "2025-10-15T21:02:15+09:00",
      "images": [
        "https://assets6.cre.ma/p/biteme-co-kr/reviews/00/00/59/17/09/image1/14c1228cfbdbe489.webp"
      ],
      "content_ja": "大きいサイズと小さいサイズ両方使ってるので、追加で購入しました～✨\n実際の色がもう少し濃いめですね。マスタードっぽい感じ？\n幼稚園のお弁当として持ち歩くのにぴったりです💛",
      "content_en": "I was already using both the large and small sizes well, so I bought an additional one ✌️ The actual color is a bit deeper—kind of like mustard? It's perfect for carrying as a daycare lunch container 💛",
      "videos": []
    },
    {
      "id": "591132",
      "rating": 5,
      "name": "김****",
      "content": "세일하길래 담아봤습니다. 처음엔 불량 제품을 받았는데 긴 연휴를 앞두고 있어서 맞교환 요청했고 다행히 이번에 받은건 정상 제품이네요 :) 잘 쓰게 되면 다음엔 다른 컬러로 또 주문해 볼게요!",
      "date": "2025-09-30T23:32:58+09:00",
      "images": [
        "https://assets6.cre.ma/p/biteme-co-kr/reviews/00/00/59/11/32/image1/4260082484d6b440.webp"
      ],
      "content_ja": "セール中だったので購入してみました。最初は不良品を受け取ってしまったんですが、長い連休を控えていたので交換を申し込んだところ、幸いなことに今回受け取った商品は正常品でした😊 問題なく使えたら、次は別の色でもう一度注文してみようと思います！",
      "content_en": "I grabbed it since it was on sale. I initially received a defective item, but since I had a long holiday coming up, I requested an exchange and thankfully the replacement is fine :) If this works out well, I'll order another color next time!",
      "videos": []
    },
    {
      "id": "590937",
      "rating": 5,
      "name": "한****",
      "content": "구분하려고 \n작은거 하나 큰거 하나\n나중에 여행용으루 쓰려구 미리 사놔욜",
      "date": "2025-09-26T22:10:37+09:00",
      "images": [
        "https://assets6.cre.ma/p/biteme-co-kr/reviews/00/00/59/09/37/image1/c9eba0dfff4b14b3.webp"
      ],
      "content_ja": "色分けしたくて、小さいサイズ1つと大きいサイズ1つを購入しました。後々の旅行用に使うつもりで、先に買っておきました😊",
      "content_en": "Got one small and one large to keep them separate. Planning to use them for travel later, so I'm stocking up now!",
      "videos": []
    },
    {
      "id": "590053",
      "rating": 5,
      "name": "조****",
      "content": "크기도 알맞고 뚜껑도 있어서 너무 좋네요\n특히 전자렌징 사용도 가능해서 먹다남은 캔 냉장고에서 꺼내서 줄때 딱이예요\n찬거 주면 탈 날거 같아 맘이 쓰였거든요^^",
      "date": "2025-09-09T11:26:53+09:00",
      "images": [
        "https://assets6.cre.ma/p/biteme-co-kr/reviews/00/00/59/00/53/image1/7088f260ad279174.webp"
      ],
      "content_ja": "サイズもちょうどいいし、蓋もついているので本当に良いですね😊特に電子レンジも使えるので、食べ残したウェットフードを冷蔵庫から出して与える時にぴったりです。冷たいまま与えるとお腹を壊しそうで心配だったので^^",
      "content_en": "The size is just right and it comes with a lid, so I'm really happy with it! 😊 Especially since it's microwave-safe, it's perfect for taking leftover canned food out of the fridge and serving it. I was always worried about giving cold food straight from the fridge ^^",
      "videos": []
    },
    {
      "id": "589934",
      "rating": 5,
      "name": "양****",
      "content": "여행갈때 갖고 다니기 좋을거 같아욤!\n색갈도 이뻐욯ㅎ",
      "date": "2025-09-05T20:55:24+09:00",
      "images": [
        "https://assets6.cre.ma/p/biteme-co-kr/reviews/00/00/58/99/34/image1/08959db967c74545.webp"
      ],
      "content_ja": "旅行に行く時に持ち運びやすそうですね！色合いも可愛いです😍",
      "content_en": "This seems great to take along when traveling! The color is pretty too 😊",
      "videos": []
    },
    {
      "id": "589502",
      "rating": 5,
      "name": "윤****",
      "content": "드뎌 샀어요\n볼때마다 사야지.. 사야지 하다 드뎌 구매했어요\n늘 보던 컬러로 세트로 구매했어요\n받고보니 조만간 이거 챙겨서 여행가고 싶어지네요",
      "date": "2025-08-29T15:39:30+09:00",
      "images": [
        "https://assets6.cre.ma/p/biteme-co-kr/reviews/00/00/58/95/02/image1/8b1c6bd7e95f89e7.webp"
      ],
      "content_ja": "やっと買いました！見るたびに「買わなきゃ、買わなきゃ」と思ってたけど、やっとゲットしました🎉いつも見てたカラーをセットで購入しました。受け取ってみたら、すぐにこれを持って旅行に行きたくなっちゃいました😄",
      "content_en": "Finally bought it! 🎉 Every time I saw it, I'd think 'I should get that... I should get that' and finally I did! I got it in my favorite color as a set. Now that I have it, I'm already thinking about taking it on a trip soon!",
      "videos": []
    },
    {
      "id": "587446",
      "rating": 5,
      "name": "신****",
      "content": "비슷한 제품 보다가 바잇미에서 발견하고 바로 구매했어요. 뚜껑이 있어서 위생적이고 외출시에 휴대도 되니 편해요. 색깔도 디자인도 너무 예뻐요.",
      "date": "2025-08-01T15:43:41+09:00",
      "images": [
        "https://assets6.cre.ma/p/biteme-co-kr/reviews/00/00/58/74/46/image1/2d11c0c2549942f9.webp",
        "https://assets6.cre.ma/p/biteme-co-kr/reviews/00/00/58/74/46/image2/e0c43cfe897dca87.webp"
      ],
      "content_ja": "似た商品を見ていたんですが、バイトミで見つけてすぐに購入しました。蓋があるので衛生的ですし、外出時の持ち運びも便利です。色合いもデザインも本当に素敵です💕",
      "content_en": "I came across this on BITE ME while looking at similar products and bought it right away. It's hygienic because it has a lid, and it's convenient to carry when going out. The color and design are so pretty too.",
      "videos": []
    },
    {
      "id": "586046",
      "rating": 5,
      "name": "세****",
      "content": "그전엔 유리그릇이였는데 달그락소리에 무서워해서 바로 실리콘으로 바꿔줬어요 다행이 무서워하지않아요 뚜껑도있어서 좋아요",
      "date": "2025-07-16T00:27:59+09:00",
      "images": [
        "https://assets6.cre.ma/p/biteme-co-kr/reviews/00/00/58/60/46/image1/54af3cbdfd9cf59f.webp"
      ],
      "content_ja": "前はガラスの食器を使ってたんですが、カチカチという音に怖がってたので、すぐにシリコンに変えてあげました。幸い怖がらなくなりました！蓋もあるので良いですね👍",
      "content_en": "Before this, we used a glass bowl, but he got scared of the clinking sound, so I switched to silicone right away. Thankfully, he's not scared anymore. And I really like that it has a lid too!",
      "videos": []
    },
    {
      "id": "585961",
      "rating": 5,
      "name": "조****",
      "content": "말랑말랑하고 무게감은 있어서 안정적이고 좋아요",
      "date": "2025-07-15T13:21:41+09:00",
      "images": [
        "https://assets6.cre.ma/p/biteme-co-kr/reviews/00/00/58/59/61/image1/398d617255020d7c.webp"
      ],
      "content_ja": "やわらかいのに適度な重みがあるので安定感があって、本当に良いです😊",
      "content_en": "It's soft and has good weight to it, so it feels stable and I'm really happy with it.",
      "videos": []
    },
    {
      "id": "585672",
      "rating": 5,
      "name": "감****",
      "content": "미니 실리콘 팟 라벤더 컬러 ♡\n저희 강아지는 2.6kg여서 기본 사이즈 실리콘 팟은 좀 크더라고요! 요 미니 사이즈가 딱~\n평소에 바잇밀 먹이는데 실리콘 팟에 바로 부어서 전자레인지 돌려주면 너무 간편하고 세척도 용이해요! 미니가 손바닥 만해서 외출시에도 가방이든 쇼핑백이든 쑉 하고 넣고 다니기 좋아요~\n진짜 미니 실리콘 팟 하나 사면 두루두루 잘 쓸수 있어서 이건 꼭! 사야데여~~",
      "date": "2025-07-10T16:08:24+09:00",
      "images": [
        "https://assets6.cre.ma/p/biteme-co-kr/reviews/00/00/58/56/72/image1/f8ed28e7a158dbae.webp",
        "https://assets6.cre.ma/p/biteme-co-kr/reviews/00/00/58/56/72/image2/7c478b040ff0d222.webp",
        "https://assets6.cre.ma/p/biteme-co-kr/reviews/00/00/58/56/72/image3/609b10b639e2fa15.webp"
      ],
      "content_ja": "ミニシリコンボウル ラベンダーカラー ♡\nうちのワンちゃんは2.6kgなので、通常サイズのシリコンボウルはちょっと大きかったんです！このミニサイズが丁度いい～\n普段バイトミルで食事させてるんですが、シリコンボウルにそのまま注いで電子レンジで温めてあげると本当に便利だし、洗うのも簡単です！ミニサイズは手のひらサイズなので、外出時もバッグやショッピングバッグにさっと入れて持ち運べるのが最高～\n本当にミニシリコンボウル1個あれば色々重宝するから、これは絶対買うべきですよ～～",
      "content_en": "Mini silicone bowl in lavender color ♡ My pup is 2.6kg, so the regular size silicone bowl was a bit too big! This mini size is just perfect~ I usually feed BITE ME, and I can pour it straight into the silicone bowl and pop it in the microwave—it's so convenient and easy to clean! Since the mini fits in the palm of your hand, it's great for carrying in a bag or shopping bag when we go out~ Honestly, if you get one mini silicone bowl, you'll use it for everything, so you definitely have to get it~~",
      "videos": []
    },
    {
      "id": "585659",
      "rating": 5,
      "name": "이****",
      "content": "외출했을때 간식이나 밥 주기 좋은것 같아요~",
      "date": "2025-07-10T13:27:34+09:00",
      "images": [
        "https://assets6.cre.ma/p/biteme-co-kr/reviews/00/00/58/56/59/image1/bf0ce6c2eec795fa.webp"
      ],
      "content_ja": "外出した時のおやつやご飯をあげるのに良さそうです～",
      "content_en": "It seems really great for giving treats or meals when we're out~ 🐕",
      "videos": []
    },
    {
      "id": "585038",
      "rating": 5,
      "name": "강****",
      "content": "전부터 사고 싶었던건데 세일 알람 소식에 바로 구매했어요~~ 울강지 5키로 조금 넘는데 사이즈 딱 좋아요~ \n가끔 사료에 화식 섞여 먹이는데 남은 화식 비닐봉지에 보관했었는데 남은거 실리콘 팟에 담아서 냉장고에 보관했다 먹이니 넘 좋네요~",
      "date": "2025-06-30T12:22:55+09:00",
      "images": [
        "https://assets6.cre.ma/p/biteme-co-kr/reviews/00/00/58/50/38/image1/f0ef084fbc175803.webp",
        "https://assets6.cre.ma/p/biteme-co-kr/reviews/00/00/58/50/38/image2/890265ca86755d24.webp"
      ],
      "content_ja": "前からずっと欲しかったんですが、セール通知を見てすぐに購入しました～～うちの子は5kg少し超えるんですが、サイズがぴったりです～普段ドライフードに缶詰を混ぜて食べさせるんですが、残った缶詰をビニール袋に保管してたんです。それを今はシリコンボウルに入れて冷蔵庫に保管して食べさせるようにしたら、本当に良いですね～",
      "content_en": "I'd been wanting to get this for a while, and when I saw the sale alert, I bought it right away~~ My pup is just over 5kg, and the size is perfect~ Sometimes I mix wet food with his kibble, and I used to keep the leftovers in a plastic bag, but now I put the rest in the silicone bowl and store it in the fridge—it's so much better~",
      "videos": []
    },
    {
      "id": "584998",
      "rating": 5,
      "name": "김****",
      "content": "진작에 살껄 그랫어요!!! 미리 소분해놓고 밖에서 뚜껑만 열고 먹이려고 샀는데 색감도 넘 이쁘고 만족합미당ㅎㅎ",
      "date": "2025-06-29T14:53:06+09:00",
      "images": [
        "https://assets6.cre.ma/p/biteme-co-kr/reviews/00/00/58/49/98/image1/48f4fc27404b6725.webp"
      ],
      "content_ja": "もっと早く買えばよかった～～！！小分けにしといて、外で蓋を開けて食べさせるために買ったんですが、色合いも本当に可愛いし大満足です😆😆",
      "content_en": "I wish I'd bought this sooner!!! I got it so I could portion things out ahead of time and just open the lid to feed him when we're out, and the color is so pretty—I'm really satisfied with it ^^",
      "videos": []
    },
    {
      "id": "584873",
      "rating": 5,
      "name": "김****",
      "content": "예쁘구 밥 먹을때 부딪히는 소리가 안나서 그런지 거부감없이 잘 먹었어요",
      "date": "2025-06-26T22:31:38+09:00",
      "images": [
        "https://assets6.cre.ma/p/biteme-co-kr/reviews/00/00/58/48/73/image1/54b6042fae86467c.webp"
      ],
      "content_ja": "かわいくて、ご飯を食べるときに食器がぶつかる音がしないのか、抵抗なくよく食べてくれます",
      "content_en": "It's pretty, and since there's no clinking sound when eating, my pet eats without any hesitation!",
      "videos": []
    },
    {
      "id": "582411",
      "rating": 5,
      "name": "황****",
      "content": "색이 넘 예뻐요 흐물거리지않아서 넘 좋네요",
      "date": "2025-05-21T00:35:04+09:00",
      "images": [
        "https://assets6.cre.ma/p/biteme-co-kr/reviews/00/00/58/24/11/image1/616c3b46d714ca82.webp"
      ],
      "content_ja": "色がとってもきれいです。柔らかくないので、本当に良いですね",
      "content_en": "The color is so pretty! It doesn't get mushy, so I really love it",
      "videos": []
    },
    {
      "id": "582084",
      "rating": 5,
      "name": "신****",
      "content": "간식통으로 갖고 다니기 사이즈 딱 좋고 색상 넘 이뻐요!",
      "date": "2025-05-15T13:16:21+09:00",
      "images": [
        "https://assets6.cre.ma/p/biteme-co-kr/reviews/00/00/58/20/84/image1/96ac3298b6d3dec4.webp"
      ],
      "content_ja": "おやつ入れとして持ち歩くのにサイズがちょうど良くて、色もとってもかわいいです！",
      "content_en": "Perfect size to carry around as a treat container, and the color is so pretty!",
      "videos": []
    },
    {
      "id": "581426",
      "rating": 5,
      "name": "한****",
      "content": "말랑하고 세척하기좋아요~ 밥꾸그릇으류도 좋음",
      "date": "2025-05-11T09:38:03+09:00",
      "images": [
        "https://assets6.cre.ma/p/biteme-co-kr/reviews/00/00/58/14/26/image1/7ca6a63ec06fed14.webp"
      ],
      "content_ja": "柔らかくて洗いやすいです～ ご飯用の器としても良いです",
      "content_en": "It's soft and easy to clean~ It works great as a food bowl too",
      "videos": []
    },
    {
      "id": "580969",
      "rating": 5,
      "name": "박****",
      "content": "디자인도 귀엽고 사이즈도 너무 작지않아 좋네요",
      "date": "2025-05-04T11:19:54+09:00",
      "images": [
        "https://assets6.cre.ma/p/biteme-co-kr/reviews/00/00/58/09/69/image1/6c59db8127636add.webp"
      ],
      "content_ja": "デザインもかわいくて、サイズも小さすぎず良いですね",
      "content_en": "The design is cute and the size is just right - not too small!",
      "videos": []
    },
    {
      "id": "580128",
      "rating": 5,
      "name": "조****",
      "content": "뚜껑 닫아서 냉장보관했다가 바로 전자렌지 데우면 되는 게 너무 편하네요. 하나 써보고 좋아서 또 샀는데\n계속 사모으게 될 것 같은느낌이에요 ㅎㅎ",
      "date": "2025-04-18T22:12:11+09:00",
      "images": [
        "https://assets6.cre.ma/p/biteme-co-kr/reviews/00/00/58/01/28/image1/cfec58656289abb3.webp"
      ],
      "content_ja": "蓋をして冷蔵保管しておいて、そのまま電子レンジで温められるのが本当に便利です。一つ使ってみて良かったので、また買ってしまいました。ずっと買い続けちゃいそうな感じです ㅎㅎ",
      "content_en": "It's so convenient - I just close the lid, keep it in the fridge, and then pop it straight in the microwave to warm it up. I liked it so much after trying one that I bought another, and I feel like I'll keep buying more 😄",
      "videos": []
    },
    {
      "id": "580086",
      "rating": 5,
      "name": "앵****",
      "content": "너무 귀엽고 깜찍해요.\n사이즈가 작은게 나와서 넘 좋아요",
      "date": "2025-04-18T14:25:26+09:00",
      "images": [
        "https://assets6.cre.ma/p/biteme-co-kr/reviews/00/00/58/00/86/image1/2da7fc7b8e233bf9.webp"
      ],
      "content_ja": "本当にかわいくて、きゃっとしてます。小さいサイズが出たのでとっても良いです",
      "content_en": "It's so cute and adorable. I'm really happy it comes in a small size!",
      "videos": []
    },
    {
      "id": "579750",
      "rating": 5,
      "name": "홍****",
      "content": "말랑한 재질에 뚜껑도 있어서 집에서도 사용하기 좋고~~ 외출시에도 사료나 간식넣어서 뚜껑덮고 따로 사료 덜거나 할거없이 바로 밥먹일수 있어서 좋아용~~!!! 내돈내산 추천템입니당❤️",
      "date": "2025-04-15T15:54:20+09:00",
      "images": [
        "https://assets6.cre.ma/p/biteme-co-kr/reviews/00/00/57/97/50/image1/b1a389ddd774bc8c.webp",
        "https://assets6.cre.ma/p/biteme-co-kr/reviews/00/00/57/97/50/image2/ab27a6ed91f9e9ce.webp",
        "https://assets6.cre.ma/p/biteme-co-kr/reviews/00/00/57/97/50/image3/cb94bce898ecf35e.webp",
        "https://assets6.cre.ma/p/biteme-co-kr/reviews/00/00/57/97/50/image4/8e219d3db8dec044.webp"
      ],
      "content_ja": "柔らかい素材で蓋も付いてるので、家でも使いやすくて～～ お出かけの時もドッグフードやおやつを入れて蓋をして、わざわざフードを減らしたりすることなく、そのままご飯をあげられるのが良いです～～～！！！ 自分のお金で買った推し商品です❤️",
      "content_en": "The soft material and lid make it great for using at home~~ and when we go out, I can just fill it with kibble or treats, close the lid, and feed my pup right away without having to portion anything out separately - it's amazing!!!  This is my own purchase and I totally recommend it ❤️",
      "videos": []
    },
    {
      "id": "579485",
      "rating": 5,
      "name": "김****",
      "content": "컬러도 넘넘 예쁘고 짱짱해요. \n뚜껑 닫으니 밀폐가 잘 돼요. \n강아지 먹일 음식들 미리 준비해서 넣어서 냉장고에 둬요🐶",
      "date": "2025-04-12T21:55:28+09:00",
      "images": [
        "https://assets6.cre.ma/p/biteme-co-kr/reviews/00/00/57/94/85/image1/d057bcfe6f4e5dd0.webp"
      ],
      "content_ja": "色もとってもきれいで、しっかりしてます。蓋を閉じるとしっかり密閉されます。わんちゃんの食べ物を事前に準備して入れて、冷蔵庫に置いてます🐶",
      "content_en": "The color is so so pretty and sturdy. The lid closes perfectly and seals really well. I prepare my dog's food ahead of time, put it in, and keep it in the fridge 🐶",
      "videos": []
    },
    {
      "id": "579148",
      "rating": 5,
      "name": "소****",
      "content": "기존에 있던 실리콘팟 잘 쓰고 있었는데 미니가 나와서 갖고다닐 용으로 구매했습니다! 잘 쓸 거 같아요! 기존에도 잘 갖고다녔는데 좀 더 작아서 너무 용이 할 거 같습니다아🥰",
      "date": "2025-04-09T09:12:32+09:00",
      "images": [
        "https://assets6.cre.ma/p/biteme-co-kr/reviews/00/00/57/91/48/image1/baa3b5c8a78d13b1.webp"
      ],
      "content_ja": "もともと持ってたシリコンポットをずっと使ってたんですが、ミニサイズが出たので持ち歩き用に購入しました！良く使えそうです！もともと持ち歩いてたんですが、もっと小さいので本当に便利になりそうです🥰",
      "content_en": "I was already using the regular silicone pot and loved it, so when the mini version came out I bought it for carrying around! I think it'll work great! I was already taking the regular one with me, but this smaller size will be so much more convenient 🥰",
      "videos": []
    }
  ]
}