{
  "product_cd": "1000050395",
  "scraped_at": "2026-05-08T05:11:49.196Z",
  "total": 3,
  "reviews": [
    {
      "id": "587697",
      "rating": 5,
      "name": "한****",
      "content": "너무 귀엽고여 사이즈 교환 문제가 조금 있었는데 번거롭지 않게 다이렉트로 다 해결해주샸어여.",
      "date": "2025-08-06T16:25:35+09:00",
      "images": [
        "https://assets6.cre.ma/p/biteme-co-kr/reviews/00/00/58/76/97/image1/9b962f0398197197.webp"
      ],
      "content_ja": "すごくかわいくて、サイズ交換の問題が少しありましたが、面倒なことなく直接全部対応してくれました。",
      "content_en": "It's so cute! 🥰 There was a little issue with the sizing, but they resolved everything smoothly without any hassle.",
      "videos": []
    },
    {
      "id": "589499",
      "rating": 5,
      "name": "고****",
      "content": "비숑5.4키로 L사이즈는 넘 작아서 엑라로 교환했어요~ 정사이즈 말구 한치수 큰걸로 구매하는게 좋을것같아여",
      "date": "2025-08-29T12:58:08+09:00",
      "images": [
        "https://assets6.cre.ma/p/biteme-co-kr/reviews/00/00/58/94/99/image1/cc65e05320ff20ec.webp"
      ],
      "content_ja": "ビションが5.4キロなのでLサイズは小さすぎて、XLに交換しました～ サイズ通りじゃなくて一回り大きいサイズで購入するのがいいと思います",
      "content_en": "My Bichon is 5.4kg and the L size was too small, so I exchanged it for XL~ I'd recommend buying one size up instead of the standard size!",
      "videos": []
    },
    {
      "id": "599904",
      "rating": 5,
      "name": "김****",
      "content": "옷이 좋습니다 소재도 너무 좋아요",
      "date": "2026-02-10T16:17:14+09:00",
      "images": [],
      "content_ja": "洋服がいいです。素材もすごくいいですよ",
      "content_en": "The clothes are great! The fabric quality is really nice too.",
      "videos": []
    }
  ]
}