{
  "product_cd": "1000025386",
  "scraped_at": "2026-05-07T12:48:09.799Z",
  "total": 50,
  "reviews": [
    {
      "id": "608213",
      "rating": 5,
      "name": "고****",
      "content": "강아지가....너무나도 인형을 사랑해요...문제는 던져달라고 무한으로 물고와요 공인줄 아나봐요...ㅎㅎㅎㅎㅎ일단 튼튼하고 이뻐서 좋아요",
      "date": "2026-04-30T15:53:50+09:00",
      "images": [
        "https://assets6.cre.ma/p/biteme-co-kr/reviews/00/00/60/82/13/image1/73f835583d133479.webp"
      ],
      "content_ja": "ワンちゃんが....本当にこのぬいぐるみを大好きなんです...問題は投げてって無限に持ってくるんですよ ボール だと思ってるのかな...ｗｗｗｗｗとにかく丈夫でかわいいから良いです",
      "content_en": "My dog absolutely loves this toy... The only problem is she keeps bringing it back infinitely asking me to throw it again, like she thinks it's a ball haha. But it's sturdy and cute, so I'm happy with it!"
    },
    {
      "id": "607236",
      "rating": 5,
      "name": "네****",
      "content": "저희 강아지가 제일 좋아하는 장난감이에요 ㅎ,,ㅎ 바잇미 젤리곰 장난감만 3개나 있어요. 최근에 반려견을 키우게 된 친구한테 선물해주려고 구매했어요 ㅎㅎ 강아지가 엄청 좋아한다구 그러네요~~ 색깔별로 다 귀여워서 다른 색도 또 사고싶을정도에요 ㅎㅎ",
      "date": "2026-04-25T11:59:17+09:00",
      "images": [
        "https://assets6.cre.ma/p/biteme-co-kr/reviews/00/00/60/72/36/image1/c371159af08992f4.webp"
      ],
      "content_ja": "うちのワンちゃんが一番好きな玩具です ｈ,,ｈ バイトミ ジェリーベア の玩具だけで3個あります 最近ワンちゃんを飼い始めた友達へのプレゼント用に買ったんですよ ｈｈ ワンちゃんがとっても気に入ってるって言ってました〜〜 色ごとにみんなかわいいから、他の色も買いたいくらいです ｈｈ",
      "content_en": "It's our dog's favorite toy 😄 We actually have 3 BITE ME jelly bear toys! I bought this one recently as a gift for a friend who just got their first dog, and they said their pup absolutely loves it~~ All the colors are so adorable that I want to buy the other colors too hehe"
    },
    {
      "id": "605207",
      "rating": 5,
      "name": "홍****",
      "content": "솜이는 맨날 노란곰이랑 자요 ㅋㅋ 귀엽지않나요ㅠ애착인형이 되어버린 노란젤리곰.. 노란색이어서 밤에 찾기도 좋은거같더라구요! 항상 잘 가지고 놀아서 좋아요 ⭐️😚⭐️",
      "date": "2026-04-03T23:07:26+09:00",
      "images": [
        "https://assets6.cre.ma/p/biteme-co-kr/reviews/00/00/60/52/07/image1/ab6e92f9cde04267.webp",
        "https://assets6.cre.ma/p/biteme-co-kr/reviews/00/00/60/52/07/image2/62e365d23c4f5202.webp"
      ],
      "content_ja": "ソミは毎日黄色いクマと寝てます ｋｋ かわいくないですか？ｓ 思い入れのあるぬいぐるみになっちゃった黄色いジェリーベア..黄色だから夜でも探しやすくていいみたいです！ いつも上手に遊んでくれてるから良いです ⭐️😚⭐️",
      "content_en": "Somyi sleeps with the yellow bear every day lol Isn't that cute?😭 The yellow jelly bear has become her comfort toy.. And since it's yellow, it's easy to find at night! She always plays with it well, which is great ⭐️😚⭐️"
    },
    {
      "id": "602864",
      "rating": 5,
      "name": "네****",
      "content": "택배받자마자 줬는데 너믄잘가지고놀아요",
      "date": "2026-03-04T20:25:56+09:00",
      "images": [
        "https://assets6.cre.ma/p/biteme-co-kr/reviews/00/00/60/28/64/image1/1a77d4bd9f815001.webp"
      ],
      "content_ja": "配送されてすぐにあげたんですけど本当によく遊んでます",
      "content_en": "I gave it to her right after getting the delivery and she plays with it so well"
    },
    {
      "id": "599084",
      "rating": 5,
      "name": "네****",
      "content": "강아지들이 노랑색을 좋아한다고 들었어요 검게 보이는 세상에서 노랑색은 뭔가 더 조금은 튀어보이는건지 모르겠어요 아무튼 너무 좋아합니다 하리보같아요",
      "date": "2026-02-04T12:51:15+09:00",
      "images": [
        "https://assets6.cre.ma/p/biteme-co-kr/reviews/00/00/59/90/84/image1/61788a2aac0bd0a4.webp"
      ],
      "content_ja": "ワンちゃんたちは黄色が好きって聞きました 暗く見える世界で黄色は何かもっと少し目立つのかな...よくわかりませんが とにかく大好きです ハリボのみたいです",
      "content_en": "I heard dogs love the color yellow. I'm not sure if it's because the world looks dark to them and yellow stands out more, but anyway we love it! It looks like a Haribo bear"
    },
    {
      "id": "597671",
      "rating": 1,
      "name": "네****",
      "content": "너무 약해서 금방 터졌어요….",
      "date": "2026-01-27T19:51:24+09:00",
      "images": [
        "https://assets6.cre.ma/p/biteme-co-kr/reviews/00/00/59/76/71/image1/2fd8d41d254d18c8.webp"
      ],
      "content_ja": "すごく弱くてすぐに破けちゃいました....",
      "content_en": "It was too fragile and broke quickly..."
    },
    {
      "id": "597891",
      "rating": 5,
      "name": "네****",
      "content": "가성비가 좋진 않은데\n강아지의 유일한 낙 장난감이니 사줍닌다.",
      "date": "2026-01-25T21:52:09+09:00",
      "images": [
        "https://assets6.cre.ma/p/biteme-co-kr/reviews/00/00/59/78/91/image1/c86a755db1ab88c1.webp"
      ],
      "content_ja": "コスパは良くないんですけど\nワンちゃんの唯一の楽しみ 玩具だから買ってあげます",
      "content_en": "It's not the best value for money, but it's my dog's only source of joy so I keep buying it for her."
    },
    {
      "id": "598105",
      "rating": 5,
      "name": "네****",
      "content": "잘가지고놀아요 잘가지고놀아요",
      "date": "2026-01-24T12:46:17+09:00",
      "images": [
        "https://assets6.cre.ma/p/biteme-co-kr/reviews/00/00/59/81/05/image1/399a604991920be1.webp"
      ],
      "content_ja": "よく遊んでます よく遊んでます",
      "content_en": "She plays with it well, plays with it well"
    },
    {
      "id": "595430",
      "rating": 5,
      "name": "장****",
      "content": "넘 귀엽뽀짝하고 가볍고 좋아요 😀 😍",
      "date": "2025-12-22T17:14:24+09:00",
      "images": [
        "https://assets6.cre.ma/p/biteme-co-kr/reviews/00/00/59/54/30/image1/82a41399f24cb375.webp"
      ],
      "content_ja": "すごくかわいくてぽかぽかして、軽くて良いです 😀 😍",
      "content_en": "It's so cute and fluffy, light, and I love it 😀 😍"
    },
    {
      "id": "593574",
      "rating": 5,
      "name": "임****",
      "content": "하나씩 뜯어주려고 샀어요 ㅎㅎ",
      "date": "2025-11-16T08:31:56+09:00",
      "images": [
        "https://assets6.cre.ma/p/biteme-co-kr/reviews/00/00/59/35/74/image1/4f6423afc72238a7.webp"
      ],
      "content_ja": "一個ずつ与えようと買いました ｈｈ",
      "content_en": "I bought it so I could give her one piece at a time hehe"
    },
    {
      "id": "593005",
      "rating": 5,
      "name": "이****",
      "content": "삑삑이를 워낙 좋아해서 집에 인형이 많음에도 불구하고 또 구입하게 됐네요. 우리 강아지 아주 좋아해요.~~^^",
      "date": "2025-11-06T17:46:42+09:00",
      "images": [
        "https://assets6.cre.ma/p/biteme-co-kr/reviews/00/00/59/30/05/image1/00d18c68df75706b.webp"
      ],
      "content_ja": "ピッピが大好きなので、家に人形がたくさんあるのに、つい買ってしまいました。うちのワンちゃんすごく気に入ってます。~~^^",
      "content_en": "Ppippi is such a favorite that even though we have lots of toys at home, we ended up buying another one. Our pup absolutely loves it.~~^^"
    },
    {
      "id": "592086",
      "rating": 5,
      "name": "남****",
      "content": "삑삑이 좋아해서 잘 가지고 놀아요",
      "date": "2025-10-21T20:01:00+09:00",
      "images": [
        "https://assets6.cre.ma/p/biteme-co-kr/reviews/00/00/59/20/86/image1/29f44b69af381873.webp"
      ],
      "content_ja": "ピッピが好きで、よく遊んでます",
      "content_en": "Our dog loves the squeaky toy and plays with it well."
    },
    {
      "id": "583865",
      "rating": 5,
      "name": "송****",
      "content": "초록색 터져서 노랭이도 사줘써용",
      "date": "2025-06-13T16:42:41+09:00",
      "images": [
        "https://assets6.cre.ma/p/biteme-co-kr/reviews/00/00/58/38/65/image1/0605857180874501.webp"
      ],
      "content_ja": "緑色が破れちゃったので、黄色いのも買ってください",
      "content_en": "The green one burst, so I got the yellow one too."
    },
    {
      "id": "571519",
      "rating": 5,
      "name": "차****",
      "content": "인스타에서 보고 너무 귀여워서 사줬는데 \n배송오자마자 졸졸 따라다니면서 기다리더라고요 ㅋㅋ\n지금도 너무 잘 갖고 놀고 있어요~☺️ \n아직 삑삑 소리는 못 내지만… 던지면 뛰어가서\n물고오고 완전 좋아해요!!\n조그만해서 물고다니기 좋으니 더 좋아하는거 같아요 :)\n나중에 또 사줘야겠어요 ~~",
      "date": "2025-01-14T19:18:45+09:00",
      "images": [
        "https://assets6.cre.ma/p/biteme-co-kr/reviews/00/00/57/15/19/image1/940b1d3b65f54ef3.webp"
      ],
      "content_ja": "インスタで見てすごく可愛いから買ってあげたんですけど、配送が来たらすぐについてきて待ってるんですよ ㅋㅋ今もすごく大事に遊んでます~☺️ まだピッピという音は出してないんですが…投げたら走って行って咥えて持ってきて、本当に大好きです!!小さいから咥えて持ち歩きやすいのか、もっと好きみたいです :)今度また買ってあげないとな ~~",
      "content_en": "I saw it on Instagram and thought it was so cute, so I got it for my dog. As soon as the package arrived, he followed me around waiting for it ㅋㅋ He's playing with it so well now~☺️ He hasn't figured out how to make the squeaky sound yet... but when I throw it, he runs after it and brings it back. He absolutely loves it!! I think he likes it even more because it's small and easy to carry around :) I'll have to get him another one later ~~"
    },
    {
      "id": "570772",
      "rating": 5,
      "name": "박****",
      "content": "오렌지색 스노클링베어 너무 좋아하길래 이거 빨간색 사줬더니 잘 가지고 놀아서 색깔별로 구매해요. 천은 약한 편인거 같아요. 벌써 세 번이나 꼬매줬어요.",
      "date": "2025-01-07T20:54:40+09:00",
      "images": [
        "https://assets6.cre.ma/p/biteme-co-kr/reviews/00/00/57/07/72/image1/e98b70314872b55e.webp"
      ],
      "content_ja": "オレンジ色のスノーケリングベアがすごく好きだったから、この赤いのを買ってあげたら、よく遊んでくれたので、色別に購入してます。生地は弱い感じです。もう3回も縫い直してますよ。",
      "content_en": "My dog loved the orange snorkeling bear so much that I got him this red one and he plays with it great, so now I'm buying them in different colors. The fabric seems a bit delicate though. I've already had to sew it three times."
    },
    {
      "id": "569350",
      "rating": 5,
      "name": "정****",
      "content": "너무 귀여워요 금방 헤져서 아쉬워요",
      "date": "2024-12-24T17:55:04+09:00",
      "images": [
        "https://assets6.cre.ma/p/biteme-co-kr/reviews/00/00/56/93/50/image1/0bf410d24b4f5638.webp"
      ],
      "content_ja": "すごく可愛いのに、すぐダメになっちゃうのが残念です",
      "content_en": "It's so cute! I just wish it didn't fall apart so quickly."
    },
    {
      "id": "568999",
      "rating": 5,
      "name": "최****",
      "content": "젤리곰 삑삑이에요~ 신상 좋아하는 우리 댕댕이 ㅋㅋㅋㅋㅋ 레드 색이 아주 강렬해서 맘에 들어요 :)",
      "date": "2024-12-20T22:59:35+09:00",
      "images": [
        "https://assets6.cre.ma/p/biteme-co-kr/reviews/00/00/56/89/99/image1/accada3fe1f60182.webp",
        "https://assets6.cre.ma/p/biteme-co-kr/reviews/00/00/56/89/99/image2/fc8f291e317abea3.webp"
      ],
      "content_ja": "ジェリーベアのピッピです~ 新作好きなうちのわんちゃん ㅋㅋㅋㅋㅋ 赤色がすごくインパクト的で気に入ってます :)",
      "content_en": "It's a jelly bear squeaky toy~ Our pup loves new things ㅋㅋㅋㅋㅋ I really like the bold red color :)"
    },
    {
      "id": "567691",
      "rating": 5,
      "name": "이****",
      "content": "좋아요 사이즈도 딱이고 국내제작이라 믿고 줄수있어서 안심되요 ㅎㅎㅎ 뜯어지면 다시 재구매하러 오겠습니다 생긴것도 너무 귀엽고 사랑스러워오 ㅠㅠ ㅎㅎ 애착 인형 되었답니다 저희 강아지 ㅋㅋㅋ",
      "date": "2024-12-10T16:04:21+09:00",
      "images": [
        "https://assets6.cre.ma/p/biteme-co-kr/reviews/00/00/56/76/91/image1/ac5ad3c32ad84e59.webp"
      ],
      "content_ja": "良いですね。サイズもちょうど良いし、国内製造なので信頼して与えられて安心です ㅎㅎㅎ ボロボロになったらまた買い直しに来ます。見た目もすごく可愛いし、愛らしくて ㅠㅠ ㅎㅎ 愛着のあるぬいぐるみになっちゃいました。うちのワンちゃん ㅋㅋㅋ",
      "content_en": "Great! The size is perfect and since it's made domestically, I feel confident giving it to my dog and it puts my mind at ease ㅎㅎㅎ If it tears, I'll definitely come back and repurchase. It's so adorable and lovely looking ㅠㅠ ㅎㅎ It's become our dog's favorite toy ㅋㅋㅋ"
    },
    {
      "id": "567418",
      "rating": 5,
      "name": "박****",
      "content": "생각보다 쪼금 큰 사이즈인데 기존에 스노클링베어젤리곰 넘 잘 갖고 놀아서 구매했습니다!",
      "date": "2024-12-07T14:45:51+09:00",
      "images": [
        "https://assets6.cre.ma/p/biteme-co-kr/reviews/00/00/56/74/18/image1/57a2043a288e6602.webp"
      ],
      "content_ja": "思ったより少し大きいサイズなんですけど、前のスノーケリングベアジェリーベアがすごく良く遊んでくれたので購入しました!",
      "content_en": "It's a bit bigger than I expected, but since my dog plays so well with the snorkeling bear jelly bear, I decided to buy it!"
    },
    {
      "id": "564846",
      "rating": 5,
      "name": "허****",
      "content": "좋아하는지 계속 물고 다녀요. 인형 눈코입 너무 귀여워요.",
      "date": "2024-11-15T20:39:21+09:00",
      "images": [
        "https://assets6.cre.ma/p/biteme-co-kr/reviews/00/00/56/48/46/image1/47997261ee257bdb.webp"
      ],
      "content_ja": "好きみたいでずっと咥えて持ち歩いてます。ぬいぐるみの目、鼻、口がすごく可愛いです。",
      "content_en": "He keeps carrying it around in his mouth - I think he loves it! The toy's face is so cute."
    },
    {
      "id": "563289",
      "rating": 5,
      "name": "홍****",
      "content": "평소에도 바잇미 장난감이면 환장하는 오댕이들입니다. 큰 맘 먹고 이것저것 구매했는데 역시 아이들이 너무 좋아하네요. 가격은 비싼 편이지만 아이들이 좋아해서 마음에 쏙 들어요.",
      "date": "2024-11-06T19:42:39+09:00",
      "images": [
        "https://assets6.cre.ma/p/biteme-co-kr/reviews/00/00/56/32/89/image1/4d2030a8ec1c7ff2.webp",
        "https://assets6.cre.ma/p/biteme-co-kr/reviews/00/00/56/32/89/image2/4f2b91c64ed0928c.webp"
      ],
      "content_ja": "普段からバイトミのおもちゃなら大好きなオデンちゃんたち。思い切っていろいろ買ってみたら、やっぱりワンちゃんたちが大喜びです。お値段は少しお高めですが、ワンちゃんたちが喜んでくれるので大満足です。",
      "content_en": "Our pups are absolutely obsessed with BITE ME toys as it is. I went ahead and bought a bunch of different ones, and the kids absolutely love them! The price is a bit steep, but since the pups love them so much, I'm really happy with it."
    },
    {
      "id": "556002",
      "rating": 5,
      "name": "김****",
      "content": "오렌지 사고 넘 귀여워서 노랑 추가했어요\n색상이 쨍하니 넘 예뻐요",
      "date": "2024-09-06T10:39:31+09:00",
      "images": [
        "https://assets6.cre.ma/p/biteme-co-kr/reviews/00/00/55/60/02/image1/4b196b9b0ce047ef.webp"
      ],
      "content_ja": "オレンジを買ってすごく可愛かったから、イエローも追加しちゃいました。色合いがはっきりしていて、本当に素敵です。",
      "content_en": "I got the orange one and it was so cute that I added the yellow one too 🧡\nThe colors are so vibrant and pretty!"
    },
    {
      "id": "554781",
      "rating": 5,
      "name": "남****",
      "content": "강아지를 너무 좋아하지만 키우지는 못해서 친구 강아지 선물용으로 샀어요. 색상 다 사고 싶어서 고민하다가 골랐는데 다른 색상도 사야겠어요. 너무 귀엽네요. 삑삑이 소리도 과하지 않아서 귀 아프지 않아요.",
      "date": "2024-08-27T20:14:18+09:00",
      "images": [
        "https://assets6.cre.ma/p/biteme-co-kr/reviews/00/00/55/47/81/image1/3e47a9af0764aa78.webp"
      ],
      "content_ja": "わんちゃんが大好きだけど飼えないので、お友達のわんちゃんへのプレゼントとして買いました。全色買いたくて悩んだんですが、これにしました。でも他の色も買わなきゃですね。すごく可愛いです。ピーピー音も大きすぎなくて、耳が痛くならないのが良いです。",
      "content_en": "I love dogs but can't have one, so I bought this as a gift for my friend's dog. I was torn because I wanted to get every color, but I ended up picking one—though I think I need to buy the other colors too! It's so adorable. The squeaky sound isn't too loud either, so it doesn't hurt their ears."
    },
    {
      "id": "554272",
      "rating": 5,
      "name": "장****",
      "content": "너무 빨리 다 터져버렸습니다- 엉엉  오분만에;;  더 튼튼한 강아지 인형은 없는건가요.. ㅡㅜ",
      "date": "2024-08-21T15:40:24+09:00",
      "images": [
        "https://assets6.cre.ma/p/biteme-co-kr/reviews/00/00/55/42/72/image1/9ab2ba43c05744d1.webp"
      ],
      "content_ja": "すごく早く全部破れちゃいました…泣。5分で…もっと丈夫なわんちゃんのぬいぐるみはないんですか…",
      "content_en": "It broke way too fast 😭 Like, in five minutes... Are there no tougher dog toys out there? 😞"
    },
    {
      "id": "553696",
      "rating": 5,
      "name": "조****",
      "content": "너무 귀여운거 아닌가요 ㅋㅋㅋ 아이보다 제가 더 맘에 들어요..ㅋ",
      "date": "2024-08-16T18:02:27+09:00",
      "images": [
        "https://assets6.cre.ma/p/biteme-co-kr/reviews/00/00/55/36/96/image1/9054ecc1764d2151.webp"
      ],
      "content_ja": "こんなに可愛いおもちゃってありますか？ｗｗｗ 子どもより私の方が気に入ってるんですｗ",
      "content_en": "Isn't it just the cutest?? 😂 I love it more than my pup does.. 😆"
    },
    {
      "id": "552896",
      "rating": 5,
      "name": "나****",
      "content": "잘 안터지고 튼튼하다는 리뷰보고 파괴왕 키우는 견주로서 젤리곰 한번 사봤습니다..!\n오 정말 짱짱해요 아직 얼마안돼서 지켜봐야겠지만 집에 있는 튼튼한 장난감이랑 비슷한 느낌이라 오래 가지고 놀 수 있을거같아요 굳굳~~~\n항상 이런 인형삑삑이 장난감들은 조금만 한눈팔면 뜯어서 솜먹고 삑삑이먹는(?) 동동이땜에 잘 안터지는 장난감으로만 놀아서 약간 지겨웠는데 \n젤리곰은 색별로 다양해서 지겨울틈 없을거같아요! 만족해요!",
      "date": "2024-08-09T16:34:07+09:00",
      "images": [
        "https://assets6.cre.ma/p/biteme-co-kr/reviews/00/00/55/28/96/image1/1551889495bc0652.webp",
        "https://assets6.cre.ma/p/biteme-co-kr/reviews/00/00/55/28/96/image2/f99c14050311c986.webp",
        "https://assets6.cre.ma/p/biteme-co-kr/reviews/00/00/55/28/96/image3/816249457bc7f7a7.webp"
      ],
      "content_ja": "壊れにくくて丈夫という口コミを見て、破壊王を飼う飼い主として、ジェリーベアを試しに買ってみました。おお、本当にしっかりしてます！まだ買ったばかりなので様子を見ないといけませんが、家にある丈夫なおもちゃと似た感じなので、長く遊べそうです。いいね～～ぬいぐるみのピーピーおもちゃはちょっと目を離すとすぐにかじって綿を食べたり、ピーピー音も食べちゃったり（？）ドンドンのせいでほとんど壊れないおもちゃでしか遊ばなくなって、ちょっと飽きてたんですが、ジェリーベアは色々な色があるから飽きることがなさそうです！満足です！",
      "content_en": "I read reviews saying it doesn't tear easily and is super durable, so as someone who has a destructive chewer, I decided to try the jelly bear! Oh wow, it's really solid! Since I just got it, I'll have to keep an eye on it, but it feels similar to the other tough toys I have at home, so I think we'll get a lot of playtime out of it ✨\nUsually with these plush squeaky toys, if I look away for even a second, my pup tears it apart and eats the stuffing and squeaker 😅 Since I only have toys that don't tear easily, I was getting a bit bored with them, but the jelly bear comes in so many different colors that there's no way we'll get tired of it! I'm really satisfied!"
    },
    {
      "id": "552823",
      "rating": 5,
      "name": "김****",
      "content": "아주 귀엽습니다. 장난감 엄청 좋아하는애라 이것도 좋아해요 ㅎㅎ",
      "date": "2024-08-09T01:28:41+09:00",
      "images": [
        "https://assets6.cre.ma/p/biteme-co-kr/reviews/00/00/55/28/23/image1/40d43d9989db1df8.webp"
      ],
      "content_ja": "とても可愛いです。おもちゃが大好きなワンちゃんなので、これも大好きです ｈｈ",
      "content_en": "It's absolutely adorable. My pup loves toys, so of course she loves this one too 😄"
    },
    {
      "id": "552473",
      "rating": 5,
      "name": "김****",
      "content": "색상이 선명하니 넘 예뻐요",
      "date": "2024-08-06T19:43:09+09:00",
      "images": [
        "https://assets6.cre.ma/p/biteme-co-kr/reviews/00/00/55/24/73/image1/8f1f66ad2729337b.webp"
      ],
      "content_ja": "色合いがはっきりしていて、本当に素敵です。",
      "content_en": "The colors are so vibrant and pretty!"
    },
    {
      "id": "551988",
      "rating": 5,
      "name": "임****",
      "content": "노랑색이어서 잘 보이는지 너무 좋아해요 ㅎㅎ 주기 전부터 보고 좋아서 펄쩍 뛰더니 잡아서 삑삑 소리 계속 내면서 너무 잘 가지고 놀아요 >♡<!",
      "date": "2024-08-01T00:46:06+09:00",
      "images": [
        "https://assets6.cre.ma/p/biteme-co-kr/reviews/00/00/55/19/88/image1/cfd1f878d10cb789.webp"
      ],
      "content_ja": "黄色だからよく見えるのか、すごく気に入ってます ｈｈ あげる前から見かけて気に入っちゃったのか、ぴょんぴょん飛び跳ねて、つかんでピーピー音を出し続けながら、すごく上手に遊んでます >♡<!}",
      "content_en": "I love that it's yellow so she can see it well! 😄 Even before I gave it to her, she saw it and got so excited, jumping up and down. She won't stop squeaking it and plays with it constantly! >♡<"
    },
    {
      "id": "551609",
      "rating": 5,
      "name": "손****",
      "content": "우리 강아지 최애 장난감이에요 ㅋㅋㅋ 여러 가지 색깔 나왔으면 좋겠어요 ㅎㅎ",
      "date": "2024-07-30T10:40:16+09:00",
      "images": [
        "https://assets6.cre.ma/p/biteme-co-kr/reviews/00/00/55/16/09/image1/77f93d1e5dd3661b.webp"
      ],
      "content_ja": "うちの子の最高のお気に入りおもちゃです ｋｋｋ いろんな色が出たらいいなあと思います ｈｈ",
      "content_en": "It's my pup's favorite toy! 😆 I wish there were more color options available 😊"
    },
    {
      "id": "549673",
      "rating": 5,
      "name": "박****",
      "content": "ㅋㅋㅋㅋㅋ 엄청 좋아해요 ㅠㅠ 크기도 큼지막하고 삑삑 소리도 잘 나서 잘 가지고 노네요 👍👍",
      "date": "2024-07-13T18:49:07+09:00",
      "images": [
        "https://assets6.cre.ma/p/biteme-co-kr/reviews/00/00/54/96/73/image1/90af791e13fe0414.webp",
        "https://assets6.cre.ma/p/biteme-co-kr/reviews/00/00/54/96/73/image2/7c75521a749137f8.webp",
        "https://assets6.cre.ma/p/biteme-co-kr/reviews/00/00/54/96/73/image3/65926531d9b2db66.webp"
      ],
      "content_ja": "ははは、めっちゃ好きです😭 サイズも大きめだし、キュッキュッという音もよく出るので、よく遊んでくれますね👍👍",
      "content_en": "Haha love it so much ㅠㅠ The size is nice and big, and it squeaks really well so my pup plays with it all the time 👍👍"
    },
    {
      "id": "547586",
      "rating": 5,
      "name": "엄****",
      "content": "장난감 한창 좋아할나이 ㅋㅋㅋ\n귀여워서 힐링되요",
      "date": "2024-07-01T12:27:54+09:00",
      "images": [
        "https://assets6.cre.ma/p/biteme-co-kr/reviews/00/00/54/75/86/image1/717c3ee1123bc7ca.webp"
      ],
      "content_ja": "おもちゃが大好きな時期だから、かわいくて癒されます😄",
      "content_en": "Haha perfect age for toys! It's so cute and healing to watch"
    },
    {
      "id": "539022",
      "rating": 5,
      "name": "이****",
      "content": "너무 잘 가지고 놀아요 배송도 빨라요",
      "date": "2024-05-12T22:00:22+09:00",
      "images": [
        "https://assets6.cre.ma/p/biteme-co-kr/reviews/00/00/53/90/22/image1/90e6751bc33f5f73.webp"
      ],
      "content_ja": "本当によく遊んでくれます。配送も早かったです",
      "content_en": "My pup plays with it so well and the shipping was fast too"
    },
    {
      "id": "538938",
      "rating": 5,
      "name": "문****",
      "content": "호불호 확실한 아기인데 핥아주고 잘놀아요!",
      "date": "2024-05-12T00:17:11+09:00",
      "images": [
        "https://assets6.cre.ma/p/biteme-co-kr/reviews/00/00/53/89/38/image1/61159fd087a64bd0.webp"
      ],
      "content_ja": "好き嫌いがはっきりしている子ですが、舐めたり、よく遊んでくれます！",
      "content_en": "My baby has very specific preferences but loves licking and playing with this!"
    },
    {
      "id": "538288",
      "rating": 5,
      "name": "이****",
      "content": "우리 꼬맹이가 너무나도 좋아하는 젤리곰~~^^♡\n혼자서 물고 던지고 다시 뛰어가서 물어오고..진짜 너무 재밌어 합니다..ㅎㅎ\n보고있음 행복해지네요~~^^",
      "date": "2024-05-08T20:33:53+09:00",
      "images": [
        "https://assets6.cre.ma/p/biteme-co-kr/reviews/00/00/53/82/88/image1/511069d3fca94eb8.webp"
      ],
      "content_ja": "うちの小さい子がこのジェリーベアーをとーっても好きなんです〜😄♡\n一人でくわえたり投げたりして、また走って行って拾って来たり…本当に楽しく遊んでます😄\n見ていて幸せになりますね〜😄",
      "content_en": "My little one loves this jelly bear so much~~^^♡ Chewing it, throwing it, running after it, and bringing it back... it's honestly so much fun to watch ㅎㅎ Just looking at them play makes me happy~~^^"
    },
    {
      "id": "537935",
      "rating": 5,
      "name": "심****",
      "content": "초록이 사구 넘 이뻐서 노랑이도 구입했어요",
      "date": "2024-05-06T08:24:47+09:00",
      "images": [
        "https://assets6.cre.ma/p/biteme-co-kr/reviews/00/00/53/79/35/image1/6e199a14e043c654.webp"
      ],
      "content_ja": "緑の子がすごくかわいくて、黄色い子も購入しちゃいました",
      "content_en": "Choco looked so cute with the green one that I bought the yellow one too"
    },
    {
      "id": "537544",
      "rating": 5,
      "name": "허****",
      "content": "약간 단단한 느낌이라서 오래 물고 놀기 괜찮을 듯 싶네요.",
      "date": "2024-05-01T23:42:18+09:00",
      "images": [
        "https://assets6.cre.ma/p/biteme-co-kr/reviews/00/00/53/75/44/image1/424b3e95fba41c8d.webp"
      ],
      "content_ja": "少し硬めの感触なので、長く噛んで遊ぶのに良さそうですね",
      "content_en": "It feels pretty sturdy so it seems like it'll be great for chewing and playing for a long time."
    },
    {
      "id": "537214",
      "rating": 5,
      "name": "전****",
      "content": "가성비 좋아요\n우리아이 입에 딱. 물고다닐수 있는거\n좋아하는데 너무좋아하네요",
      "date": "2024-04-30T18:34:04+09:00",
      "images": [
        "https://assets6.cre.ma/p/biteme-co-kr/reviews/00/00/53/72/14/image1/34e5a4c6e4c01f89.webp",
        "https://assets6.cre.ma/p/biteme-co-kr/reviews/00/00/53/72/14/image2/6f62d8bc21b743fe.webp"
      ],
      "content_ja": "コスパ最高ですよ\nうちの子の口にぴったり。持ち歩いて噛めるのが\nめっちゃ気に入ってるんです",
      "content_en": "Great value for the price. Perfect fit for my pup's mouth. They can carry it around and just love it so much"
    },
    {
      "id": "536823",
      "rating": 5,
      "name": "박****",
      "content": "아주 귀여운 곰돌이!! 색깔도 쨍하고 강아지도 너무 좋아해요 주인도 좋고 강아지도 좋은 일석이조",
      "date": "2024-04-28T17:50:31+09:00",
      "images": [
        "https://assets6.cre.ma/p/biteme-co-kr/reviews/00/00/53/68/23/image1/f98351f6a4045c36.webp"
      ],
      "content_ja": "すごくかわいいクマさん！！色も鮮やかで、わんちゃんもとても気に入っています。飼い主も嬉しい、わんちゃんも嬉しい、一石二鳥です",
      "content_en": "Such a cute little bear!! The colors are so vibrant and my dog absolutely loves it. Win-win for both me and my pup!"
    },
    {
      "id": "535790",
      "rating": 5,
      "name": "노****",
      "content": "저희 아이가 너무 좋아해요 다른 색상도 사주고 싶어요 바잇미 너무 예뻐요 최고",
      "date": "2024-04-20T17:44:46+09:00",
      "images": [
        "https://assets6.cre.ma/p/biteme-co-kr/reviews/00/00/53/57/90/image1/a2ccec6ea0bc47de.webp"
      ],
      "content_ja": "うちの子がとても好きです。他の色も買ってあげたいです。バイトミーがとても可愛いです。最高",
      "content_en": "My baby loves it so much! I want to get the other colors too. BITE ME is so pretty. The best!"
    },
    {
      "id": "534401",
      "rating": 5,
      "name": "심****",
      "content": "사진 찍으려고 하니깐 뺏어가는줄 알고 지키기 모드 들어가네요 초록색 넘 귀여워요",
      "date": "2024-04-11T21:10:10+09:00",
      "images": [
        "https://assets6.cre.ma/p/biteme-co-kr/reviews/00/00/53/44/01/image1/57bc3e4423e784e3.webp"
      ],
      "content_ja": "写真を撮ろうとしたら、取られちゃうと思ったのか守る モードに入ってますね 緑色がとってもかわいいです",
      "content_en": "When I tried to take a picture, he went into guard mode thinking I was taking it away 😄 The green color is so cute!"
    },
    {
      "id": "534103",
      "rating": 5,
      "name": "최****",
      "content": "친구 강아지가 가지고 있는거 보고 주문했어요\n우리 곰돌이 첫 장난감🐻",
      "date": "2024-04-09T21:17:00+09:00",
      "images": [
        "https://assets6.cre.ma/p/biteme-co-kr/reviews/00/00/53/41/03/image1/77cb2e37b6114a05.webp"
      ],
      "content_ja": "友達のワンちゃんが持ってるのを見て注文しました\n我が家のクマちゃん初めてのおもちゃ🐻",
      "content_en": "I saw my friend's dog had one and ordered it right away. Gom's first toy ever! 🐻"
    },
    {
      "id": "532288",
      "rating": 5,
      "name": "남****",
      "content": "주황색 샀었는데 애착인형으로 잘때도 물고 와요 ㅋㅋㅋㅋ 다 뜯겨서(터그놀이도 하고 하다보니..) 레드로 재구매합니다!!",
      "date": "2024-03-29T21:59:45+09:00",
      "images": [
        "https://assets6.cre.ma/p/biteme-co-kr/reviews/00/00/53/22/88/image1/8422657edb75c863.webp",
        "https://assets6.cre.ma/p/biteme-co-kr/reviews/00/00/53/22/88/image2/9d1255cef52864fd.webp"
      ],
      "content_ja": "オレンジ色を買ってたんですけど、抱き枕としていい時も咥えてきます ㅋㅋㅋㅋ ボロボロになっちゃって(引っ張りっこもしたし...)レッドで買い直します!!",
      "content_en": "I bought the orange one before and he's so attached to it—he even sleeps with it in his mouth lol 😂 Since it got all torn up from tug of war and everything, I'm reordering in red!!"
    },
    {
      "id": "531701",
      "rating": 5,
      "name": "이****",
      "content": "색상도 쨍하니 너무 마음에 들어요 강아지장난감인데 탐나네요",
      "date": "2024-03-27T16:56:57+09:00",
      "images": [
        "https://assets6.cre.ma/p/biteme-co-kr/reviews/00/00/53/17/01/image1/35a8ede978235b81.webp"
      ],
      "content_ja": "色もハッキリしていて本当に気に入ってます わんちゃん用のおもちゃなのに欲しくなっちゃいますね",
      "content_en": "The colors are so vibrant and I love it! It's supposed to be a dog toy but I'm kinda tempted by it myself 😄"
    },
    {
      "id": "527672",
      "rating": 5,
      "name": "김****",
      "content": "웰컴딜로 구매했어요! 원래는 정가로 2개 구매하려고 했는 데 젤리곰이 100원이라네요!? 호다닥 구매 했어요 🩷",
      "date": "2024-03-03T16:38:48+09:00",
      "images": [
        "https://assets6.cre.ma/p/biteme-co-kr/reviews/00/00/52/76/72/image1/0a51eee121db3272.webp"
      ],
      "content_ja": "ウェルカムディールで買いました!元々は定価で2個買う予定だったんですけど、ジェリーベアが100円だって!? 慌てて買っちゃいました 🩷",
      "content_en": "Got it on the welcome deal! I was planning to buy 2 at full price but the jelly bear is only 100 won!? I rushed to order 🩷"
    },
    {
      "id": "527671",
      "rating": 5,
      "name": "김****",
      "content": "귀여운 젤리곰한테 삑삑이 소리가 나요! 색상별로 구매하고 싶을 만큼.. 귀엽습니다 지갑 탕진이요 ㅜㅜ",
      "date": "2024-03-03T16:38:01+09:00",
      "images": [
        "https://assets6.cre.ma/p/biteme-co-kr/reviews/00/00/52/76/71/image1/5b56d27ec0688014.webp"
      ],
      "content_ja": "かわいいジェリーベアからピッピって音がします!色ごとに買いたくなるくらい...かわいいです お財布が大変です ㅜㅜ",
      "content_en": "The cute jelly bear makes a squeaky sound! I want to buy it in every color... it's just so adorable 😭 My wallet is crying ㅜㅜ"
    },
    {
      "id": "526231",
      "rating": 5,
      "name": "이****",
      "content": "오렌지색 곰돌이 너무 이뻐요~^^\n신기한것이 꺼내주자마자 물고 뛰어다니면서 혼자 놀더니..잠들기도 하구요 ㅎㅎ\n일단 가벼워서 좋은가봐요~\n근데 몇번 안물었는데 벌써 등이 터져서 꼬매줬네요..^^;;\n재봉이 더 튼튼하면 좋겠어요~~",
      "date": "2024-02-22T17:26:06+09:00",
      "images": [
        "https://assets6.cre.ma/p/biteme-co-kr/reviews/00/00/52/62/31/image1/89d489781f7f122d.webp"
      ],
      "content_ja": "オレンジ色のクマちゃんほんとに可愛いです~^^\n取り出したとたんに咥えて走り回りながら1人で遊んでるし...寝たりもするし ㅎㅎ\nとにかく軽いから気に入ってるみたいです~\nでも数回咥えただけなのに背中がもう破れちゃったので縫い直しちゃいました..^^;;\n縫製がもっと丈夫だといいんですけど~~",
      "content_en": "The orange bear is so pretty~^^ As soon as I took it out, he grabbed it and ran around playing by himself... and then took a nap with it lol 😄 It seems he likes that it's lightweight~ But after just a few bites, the back already ripped so I had to sew it up ^^;; I wish the stitching were more durable~~"
    },
    {
      "id": "525665",
      "rating": 5,
      "name": "허****",
      "content": "레드 그린 구매하고 옐로우도 구매",
      "date": "2024-02-19T15:10:04+09:00",
      "images": [
        "https://assets6.cre.ma/p/biteme-co-kr/reviews/00/00/52/56/65/image1/28bf5f4c88ac3a31.webp"
      ],
      "content_ja": "レッドとグリーンを買ってイエローも買いました",
      "content_en": "Bought red and green, then also got yellow"
    },
    {
      "id": "525091",
      "rating": 5,
      "name": "김****",
      "content": "색상도 예쁘고 선명하고 요즘 유행하는 젤리곰 딱 그 느낌이예요 ㅎㅎ",
      "date": "2024-02-15T20:53:33+09:00",
      "images": [
        "https://assets6.cre.ma/p/biteme-co-kr/reviews/00/00/52/50/91/image1/c9278724ab17e151.webp",
        "https://assets6.cre.ma/p/biteme-co-kr/reviews/00/00/52/50/91/image2/db8ec797caab11c7.webp",
        "https://assets6.cre.ma/p/biteme-co-kr/reviews/00/00/52/50/91/image3/a7392ddeeb4f8c53.webp"
      ],
      "content_ja": "色も可愛いし鮮やかで、最近流行のジェリーベアそのものですね ㅎㅎ",
      "content_en": "The colors are pretty and vivid—it's got that trendy jelly bear vibe! 😄"
    },
    {
      "id": "523948",
      "rating": 5,
      "name": "김****",
      "content": "이번에 주문한 장난감들 펼쳐두고 고르라고 하니까 냉큼 집어서 돌아다니는데 곰인형이라 너무 귀엽더라고요~ 담번에 다른 색상도 주문할게요 🧸",
      "date": "2024-02-06T21:23:33+09:00",
      "images": [
        "https://assets6.cre.ma/p/biteme-co-kr/reviews/00/00/52/39/48/image1/5ea9df7eda05b9f5.webp"
      ],
      "content_ja": "今回注文したおもちゃを並べて選ばせたら、さっさとつかんで持ち歩いてるんですけど、クマのぬいぐるみだから本当にかわいいですね~ 次は別の色も注文します 🧸",
      "content_en": "I laid out all the toys I ordered and told him to pick one, and he quickly grabbed the bear and ran off with it—it's just so cute because it's a bear plush! 🧸 I'll order other colors next time"
    }
  ]
}